sequtils_test/__init__.py
sequtils_test/sequtils.py
sequtils_test-0.1.1.dist-info/LICENSE
sequtils_test-0.1.1.dist-info/METADATA
sequtils_test-0.1.1.dist-info/WHEEL
sequtils_test-0.1.1.dist-info/top_level.txt
sequtils_test-0.1.1.dist-info/RECORD
