Metadata-Version: 2.1
Name: sequtils-test
Version: 0.1.1
Summary: Sequtils test
Author-email: nbrg-ppcu <nbrg@itk.ppke.hu>
Project-URL: Homepage, https://github.com/nbrg-ppcu/sequtils_test
Project-URL: Bug Tracker, https://github.com/nbrg-ppcu/sequtils_test/issues
Classifier: Programming Language :: Python :: 3
Classifier: License :: OSI Approved :: MIT License
Classifier: Operating System :: OS Independent
Requires-Python: >=3.7
License-File: LICENSE
Requires-Dist: biopython (>=1.79)
Requires-Dist: pandas (>=1.4.4)
